myst/__init__.py
myst_cli-0.0.1.dist-info/LICENSE
myst_cli-0.0.1.dist-info/METADATA
myst_cli-0.0.1.dist-info/WHEEL
myst_cli-0.0.1.dist-info/top_level.txt
myst_cli-0.0.1.dist-info/RECORD
